src/soxaitool/src/DM.py
src/soxaitool/src/IO.py
src/soxaitool/src/PLOT.py
src/soxaitool/src/RING.py
src/soxaitool/src/__initial__.py
soxaitool-0.0.6.dist-info/METADATA
soxaitool-0.0.6.dist-info/WHEEL
soxaitool-0.0.6.dist-info/entry_points.txt
soxaitool-0.0.6.dist-info/license_files/LICENSE
soxaitool-0.0.6.dist-info/RECORD
